arduiglitch/__init__.py
arduiglitch-0.1.3.dist-info/LICENSE
arduiglitch-0.1.3.dist-info/METADATA
arduiglitch-0.1.3.dist-info/WHEEL
arduiglitch-0.1.3.dist-info/entry_points.txt
arduiglitch-0.1.3.dist-info/top_level.txt
arduiglitch-0.1.3.dist-info/RECORD
