Metadata-Version: 2.1
Name: arduiglitch
Version: 0.1.3
Summary: Python module for the eponym voltage glitch training. Contains everything required to run the tutorials.
Author-email: Hugo Perrin <h.perrin@emse.fr>
License: GPL-3.0-or-later
Requires-Python: >=3.10.12
License-File: LICENSE
Requires-Dist: pyyaml
Requires-Dist: pyserial
Requires-Dist: numpy
Requires-Dist: pandas
Requires-Dist: wrapt
Requires-Dist: blessed
Requires-Dist: flask
Requires-Dist: sphinx
Requires-Dist: sphinx-autodoc-typehints
